pylabs/__init__.py
pylabs/pylabs.py
pylabs-0.0.1.dist-info/METADATA
pylabs-0.0.1.dist-info/WHEEL
pylabs-0.0.1.dist-info/top_level.txt
pylabs-0.0.1.dist-info/RECORD
