Metadata-Version: 2.1
Name: pylabs
Version: 0.0.1
Summary: This class provides methodes for using PyLabs API
Home-page: UNKNOWN
Author: Andreas Ziegler, Benjamin Dollinger
Author-email: mail@pylabs.de
License: MIT
Platform: UNKNOWN
